{
  "tweets": [
    {
      "created_at": "Mon Nov 14 07:23:04 +0000 2016",
      "id": 798063684257857500,
      "id_str": "798063684257857536",
      "text": "Всем привет! Эту неделю с вами немного пообщается редакция – мы тут совсем недавно вернулись @DevGAMM и хотим поделиться впечатлениями :)",
      "truncated": false,
      "entities": {
        "hashtags": [],
        "symbols": [],
        "user_mentions": [
          {
            "screen_name": "DevGAMM",
            "name": "#DevGAMM Minsk ✈️",
            "id": 23060987,
            "id_str": "23060987",
            "indices": [
              93,
              101
            ]
          }
        ],
        "urls": []
      },
      "source": "<a href=\"http://twitter.com\" rel=\"nofollow\">Twitter Web Client</a>",
      "in_reply_to_status_id": null,
      "in_reply_to_status_id_str": null,
      "in_reply_to_user_id": null,
      "in_reply_to_user_id_str": null,
      "in_reply_to_screen_name": null,
      "user": {
        "id": 747371158832545800,
        "id_str": "747371158832545792"
      },
      "geo": null,
      "coordinates": null,
      "place": null,
      "contributors": null,
      "is_quote_status": false,
      "retweet_count": 0,
      "favorite_count": 3,
      "favorited": false,
      "retweeted": false,
      "lang": "ru"
    },
    {
      "created_at": "Mon Nov 14 07:24:32 +0000 2016",
      "id": 798064053465665500,
      "id_str": "798064053465665536",
      "text": "Спасибо большое Игорю @Oxeren за шикарнейшую неделю! У него сегодня, кстати, День Рождения! Поздравляем, Игорь! Желаем успеха и денег! :D",
      "truncated": false,
      "entities": {
        "hashtags": [],
        "symbols": [],
        "user_mentions": [
          {
            "screen_name": "Oxeren",
            "name": "Igor Rashkuev",
            "id": 991226479,
            "id_str": "991226479",
            "indices": [
              22,
              29
            ]
          }
        ],
        "urls": []
      },
      "source": "<a href=\"http://twitter.com\" rel=\"nofollow\">Twitter Web Client</a>",
      "in_reply_to_status_id": null,
      "in_reply_to_status_id_str": null,
      "in_reply_to_user_id": null,
      "in_reply_to_user_id_str": null,
      "in_reply_to_screen_name": null,
      "user": {
        "id": 747371158832545800,
        "id_str": "747371158832545792"
      },
      "geo": null,
      "coordinates": null,
      "place": null,
      "contributors": null,
      "is_quote_status": false,
      "retweet_count": 0,
      "favorite_count": 2,
      "favorited": false,
      "retweeted": false,
      "lang": "ru"
    },
    {
      "created_at": "Mon Nov 14 07:28:10 +0000 2016",
      "id": 798064970206281700,
      "id_str": "798064970206281728",
      "text": "Сплошные праздники и в редакции – сегодня ДР у Саши Пашина, да и у Вовы @VKSpaz он был недавно. В общем, всех поздравляем, всем мира :)",
      "truncated": false,
      "entities": {
        "hashtags": [],
        "symbols": [],
        "user_mentions": [
          {
            "screen_name": "VKSpaz",
            "name": "Vladimir Kovtun",
            "id": 127288264,
            "id_str": "127288264",
            "indices": [
              72,
              79
            ]
          }
        ],
        "urls": []
      },
      "source": "<a href=\"http://twitter.com\" rel=\"nofollow\">Twitter Web Client</a>",
      "in_reply_to_status_id": null,
      "in_reply_to_status_id_str": null,
      "in_reply_to_user_id": null,
      "in_reply_to_user_id_str": null,
      "in_reply_to_screen_name": null,
      "user": {
        "id": 747371158832545800,
        "id_str": "747371158832545792"
      },
      "geo": null,
      "coordinates": null,
      "place": null,
      "contributors": null,
      "is_quote_status": false,
      "retweet_count": 0,
      "favorite_count": 0,
      "favorited": false,
      "retweeted": false,
      "lang": "ru"
    },
    {
      "created_at": "Mon Nov 14 07:31:39 +0000 2016",
      "id": 798065846484607000,
      "id_str": "798065846484606976",
      "text": "На затравку вам фоточка с Анти-Линча вместе с прекрасной @lerika, \"мамой\" @DevGAMM :3 https://t.co/eV99V9wzcW",
      "truncated": false,
      "entities": {
        "hashtags": [],
        "symbols": [],
        "user_mentions": [
          {
            "screen_name": "lerika",
            "name": "Lerika is happy! 😘",
            "id": 14742525,
            "id_str": "14742525",
            "indices": [
              57,
              64
            ]
          },
          {
            "screen_name": "DevGAMM",
            "name": "#DevGAMM Minsk ✈️",
            "id": 23060987,
            "id_str": "23060987",
            "indices": [
              74,
              82
            ]
          }
        ],
        "urls": [],
        "media": [
          {
            "id": 798065297282494500,
            "id_str": "798065297282494464",
            "indices": [
              86,
              109
            ],
            "media_url": "http://pbs.twimg.com/media/CxNMKNgW8AAKs1V.jpg",
            "media_url_https": "https://pbs.twimg.com/media/CxNMKNgW8AAKs1V.jpg",
            "url": "https://t.co/eV99V9wzcW",
            "display_url": "pic.twitter.com/eV99V9wzcW",
            "expanded_url": "https://twitter.com/gdunderhood/status/798065846484606976/photo/1",
            "type": "photo",
            "sizes": {
              "large": {
                "w": 960,
                "h": 640,
                "resize": "fit"
              },
              "medium": {
                "w": 960,
                "h": 640,
                "resize": "fit"
              },
              "thumb": {
                "w": 150,
                "h": 150,
                "resize": "crop"
              },
              "small": {
                "w": 680,
                "h": 453,
                "resize": "fit"
              }
            }
          }
        ]
      },
      "extended_entities": {
        "media": [
          {
            "id": 798065297282494500,
            "id_str": "798065297282494464",
            "indices": [
              86,
              109
            ],
            "media_url": "http://pbs.twimg.com/media/CxNMKNgW8AAKs1V.jpg",
            "media_url_https": "https://pbs.twimg.com/media/CxNMKNgW8AAKs1V.jpg",
            "url": "https://t.co/eV99V9wzcW",
            "display_url": "pic.twitter.com/eV99V9wzcW",
            "expanded_url": "https://twitter.com/gdunderhood/status/798065846484606976/photo/1",
            "type": "photo",
            "sizes": {
              "large": {
                "w": 960,
                "h": 640,
                "resize": "fit"
              },
              "medium": {
                "w": 960,
                "h": 640,
                "resize": "fit"
              },
              "thumb": {
                "w": 150,
                "h": 150,
                "resize": "crop"
              },
              "small": {
                "w": 680,
                "h": 453,
                "resize": "fit"
              }
            }
          }
        ]
      },
      "source": "<a href=\"http://twitter.com\" rel=\"nofollow\">Twitter Web Client</a>",
      "in_reply_to_status_id": null,
      "in_reply_to_status_id_str": null,
      "in_reply_to_user_id": null,
      "in_reply_to_user_id_str": null,
      "in_reply_to_screen_name": null,
      "user": {
        "id": 747371158832545800,
        "id_str": "747371158832545792"
      },
      "geo": null,
      "coordinates": null,
      "place": null,
      "contributors": null,
      "is_quote_status": false,
      "retweet_count": 0,
      "favorite_count": 1,
      "favorited": false,
      "retweeted": false,
      "possibly_sensitive": false,
      "lang": "ru"
    },
    {
      "created_at": "Mon Nov 14 07:32:31 +0000 2016",
      "id": 798066064294744000,
      "id_str": "798066064294744064",
      "text": "Анти-Линч, кстати, мы провели с @YarKravtsov и @retropcan, которых вы тоже имели удовольствие читать в андерхуде – но обо всем по порядку :)",
      "truncated": false,
      "entities": {
        "hashtags": [],
        "symbols": [],
        "user_mentions": [
          {
            "screen_name": "YarKravtsov",
            "name": "Yaroslav Kravtsov",
            "id": 2248341073,
            "id_str": "2248341073",
            "indices": [
              32,
              44
            ]
          },
          {
            "screen_name": "retropcan",
            "name": "Svyatoslav Torick",
            "id": 904657574,
            "id_str": "904657574",
            "indices": [
              47,
              57
            ]
          }
        ],
        "urls": []
      },
      "source": "<a href=\"http://twitter.com\" rel=\"nofollow\">Twitter Web Client</a>",
      "in_reply_to_status_id": 798065846484607000,
      "in_reply_to_status_id_str": "798065846484606976",
      "in_reply_to_user_id": 747371158832545800,
      "in_reply_to_user_id_str": "747371158832545792",
      "in_reply_to_screen_name": "gdunderhood",
      "user": {
        "id": 747371158832545800,
        "id_str": "747371158832545792"
      },
      "geo": null,
      "coordinates": null,
      "place": null,
      "contributors": null,
      "is_quote_status": false,
      "retweet_count": 0,
      "favorite_count": 0,
      "favorited": false,
      "retweeted": false,
      "lang": "ru"
    },
    {
      "created_at": "Mon Nov 14 08:13:27 +0000 2016",
      "id": 798076366281445400,
      "id_str": "798076366281445376",
      "text": "#DevGAMM'16 Minsk — прекрасен. Это несомненно. Но есть и отрицательные стороны. Что вам не понравилось? Давайте соберём для оргов фидбек?",
      "truncated": false,
      "entities": {
        "hashtags": [
          {
            "text": "DevGAMM",
            "indices": [
              0,
              8
            ]
          }
        ],
        "symbols": [],
        "user_mentions": [],
        "urls": []
      },
      "source": "<a href=\"http://twitter.com\" rel=\"nofollow\">Twitter Web Client</a>",
      "in_reply_to_status_id": null,
      "in_reply_to_status_id_str": null,
      "in_reply_to_user_id": null,
      "in_reply_to_user_id_str": null,
      "in_reply_to_screen_name": null,
      "user": {
        "id": 747371158832545800,
        "id_str": "747371158832545792"
      },
      "geo": null,
      "coordinates": null,
      "place": null,
      "contributors": null,
      "is_quote_status": false,
      "retweet_count": 0,
      "favorite_count": 1,
      "favorited": false,
      "retweeted": false,
      "lang": "ru"
    },
    {
      "created_at": "Mon Nov 14 09:05:49 +0000 2016",
      "id": 798089542557433900,
      "id_str": "798089542557433857",
      "text": "Если у вас после #DevGAMM оказались визитки «МанжетГД», то это значит, что вам стоит написать гостевую статью о своей игре и ГД в ней ;)",
      "truncated": false,
      "entities": {
        "hashtags": [
          {
            "text": "DevGAMM",
            "indices": [
              17,
              25
            ]
          }
        ],
        "symbols": [],
        "user_mentions": [],
        "urls": []
      },
      "source": "<a href=\"http://twitter.com\" rel=\"nofollow\">Twitter Web Client</a>",
      "in_reply_to_status_id": null,
      "in_reply_to_status_id_str": null,
      "in_reply_to_user_id": null,
      "in_reply_to_user_id_str": null,
      "in_reply_to_screen_name": null,
      "user": {
        "id": 747371158832545800,
        "id_str": "747371158832545792"
      },
      "geo": null,
      "coordinates": null,
      "place": null,
      "contributors": null,
      "is_quote_status": false,
      "retweet_count": 0,
      "favorite_count": 1,
      "favorited": false,
      "retweeted": false,
      "lang": "ru"
    },
    {
      "created_at": "Mon Nov 14 09:06:49 +0000 2016",
      "id": 798089796128243700,
      "id_str": "798089796128243712",
      "text": "А если визиток не оказалось, но вы хотите писать статьи для «МанжетГД» — всегда пожалуйста. https://t.co/PeWK4mNLPF",
      "truncated": false,
      "entities": {
        "hashtags": [],
        "symbols": [],
        "user_mentions": [],
        "urls": [
          {
            "url": "https://t.co/PeWK4mNLPF",
            "expanded_url": "https://gdcuffs.com/guest-submit/",
            "display_url": "gdcuffs.com/guest-submit/",
            "indices": [
              92,
              115
            ]
          }
        ]
      },
      "source": "<a href=\"http://twitter.com\" rel=\"nofollow\">Twitter Web Client</a>",
      "in_reply_to_status_id": null,
      "in_reply_to_status_id_str": null,
      "in_reply_to_user_id": null,
      "in_reply_to_user_id_str": null,
      "in_reply_to_screen_name": null,
      "user": {
        "id": 747371158832545800,
        "id_str": "747371158832545792"
      },
      "geo": null,
      "coordinates": null,
      "place": null,
      "contributors": null,
      "is_quote_status": false,
      "retweet_count": 0,
      "favorite_count": 1,
      "favorited": false,
      "retweeted": false,
      "possibly_sensitive": false,
      "lang": "ru"
    },
    {
      "created_at": "Mon Nov 14 13:50:26 +0000 2016",
      "id": 798161167617261600,
      "id_str": "798161167617261568",
      "text": "Посмотрите Артему в глаза – он очень рад количеству подписчиков андерхуда :D https://t.co/zIg0h0GyKo",
      "truncated": false,
      "entities": {
        "hashtags": [],
        "symbols": [],
        "user_mentions": [],
        "urls": [],
        "media": [
          {
            "id": 798161151376969700,
            "id_str": "798161151376969729",
            "indices": [
              77,
              100
            ],
            "media_url": "http://pbs.twimg.com/media/CxOjVp1XUAE7uB6.jpg",
            "media_url_https": "https://pbs.twimg.com/media/CxOjVp1XUAE7uB6.jpg",
            "url": "https://t.co/zIg0h0GyKo",
            "display_url": "pic.twitter.com/zIg0h0GyKo",
            "expanded_url": "https://twitter.com/gdunderhood/status/798161167617261568/photo/1",
            "type": "photo",
            "sizes": {
              "medium": {
                "w": 126,
                "h": 313,
                "resize": "fit"
              },
              "large": {
                "w": 126,
                "h": 313,
                "resize": "fit"
              },
              "small": {
                "w": 126,
                "h": 313,
                "resize": "fit"
              },
              "thumb": {
                "w": 126,
                "h": 126,
                "resize": "crop"
              }
            }
          }
        ]
      },
      "extended_entities": {
        "media": [
          {
            "id": 798161151376969700,
            "id_str": "798161151376969729",
            "indices": [
              77,
              100
            ],
            "media_url": "http://pbs.twimg.com/media/CxOjVp1XUAE7uB6.jpg",
            "media_url_https": "https://pbs.twimg.com/media/CxOjVp1XUAE7uB6.jpg",
            "url": "https://t.co/zIg0h0GyKo",
            "display_url": "pic.twitter.com/zIg0h0GyKo",
            "expanded_url": "https://twitter.com/gdunderhood/status/798161167617261568/photo/1",
            "type": "photo",
            "sizes": {
              "medium": {
                "w": 126,
                "h": 313,
                "resize": "fit"
              },
              "large": {
                "w": 126,
                "h": 313,
                "resize": "fit"
              },
              "small": {
                "w": 126,
                "h": 313,
                "resize": "fit"
              },
              "thumb": {
                "w": 126,
                "h": 126,
                "resize": "crop"
              }
            }
          }
        ]
      },
      "source": "<a href=\"http://twitter.com\" rel=\"nofollow\">Twitter Web Client</a>",
      "in_reply_to_status_id": null,
      "in_reply_to_status_id_str": null,
      "in_reply_to_user_id": null,
      "in_reply_to_user_id_str": null,
      "in_reply_to_screen_name": null,
      "user": {
        "id": 747371158832545800,
        "id_str": "747371158832545792"
      },
      "geo": null,
      "coordinates": null,
      "place": null,
      "contributors": null,
      "is_quote_status": false,
      "retweet_count": 0,
      "favorite_count": 3,
      "favorited": false,
      "retweeted": false,
      "possibly_sensitive": false,
      "lang": "ru"
    },
    {
      "created_at": "Mon Nov 14 13:52:42 +0000 2016",
      "id": 798161739263123500,
      "id_str": "798161739263123456",
      "text": "Сокрушались, что нет общей фотки с ДевГамма, но вот нашлась. Из присутствовавших на этой конфе Манжет не хватает то… https://t.co/dpfKIXEDbM",
      "truncated": true,
      "entities": {
        "hashtags": [],
        "symbols": [],
        "user_mentions": [],
        "urls": [
          {
            "url": "https://t.co/dpfKIXEDbM",
            "expanded_url": "https://twitter.com/i/web/status/798161739263123456",
            "display_url": "twitter.com/i/web/status/7…",
            "indices": [
              117,
              140
            ]
          }
        ]
      },
      "source": "<a href=\"http://twitter.com\" rel=\"nofollow\">Twitter Web Client</a>",
      "in_reply_to_status_id": null,
      "in_reply_to_status_id_str": null,
      "in_reply_to_user_id": null,
      "in_reply_to_user_id_str": null,
      "in_reply_to_screen_name": null,
      "user": {
        "id": 747371158832545800,
        "id_str": "747371158832545792"
      },
      "geo": null,
      "coordinates": null,
      "place": null,
      "contributors": null,
      "is_quote_status": false,
      "retweet_count": 1,
      "favorite_count": 7,
      "favorited": false,
      "retweeted": false,
      "possibly_sensitive": false,
      "lang": "ru"
    },
    {
      "created_at": "Mon Nov 14 13:53:21 +0000 2016",
      "id": 798161902559842300,
      "id_str": "798161902559842304",
      "text": "Зато есть шикарный Женя @Mazokpixels Юдин, которого вы все наверняка знаете – он ведь рисует для половины нашего инди :D",
      "truncated": false,
      "entities": {
        "hashtags": [],
        "symbols": [],
        "user_mentions": [
          {
            "screen_name": "Mazokpixels",
            "name": "Evgeniy Yudin",
            "id": 2925863273,
            "id_str": "2925863273",
            "indices": [
              24,
              36
            ]
          }
        ],
        "urls": []
      },
      "source": "<a href=\"http://twitter.com\" rel=\"nofollow\">Twitter Web Client</a>",
      "in_reply_to_status_id": 798161739263123500,
      "in_reply_to_status_id_str": "798161739263123456",
      "in_reply_to_user_id": 747371158832545800,
      "in_reply_to_user_id_str": "747371158832545792",
      "in_reply_to_screen_name": "gdunderhood",
      "user": {
        "id": 747371158832545800,
        "id_str": "747371158832545792"
      },
      "geo": null,
      "coordinates": null,
      "place": null,
      "contributors": null,
      "is_quote_status": false,
      "retweet_count": 0,
      "favorite_count": 3,
      "favorited": false,
      "retweeted": false,
      "lang": "ru"
    },
    {
      "created_at": "Mon Nov 14 14:20:04 +0000 2016",
      "id": 798168625253417000,
      "id_str": "798168625253416960",
      "text": "Показывать на шоукейсе сложный и многоплановый проект с глубоким геймплеем крайне невыгодно, проще платформер, к примеру, где вход за 3 сек.",
      "truncated": false,
      "entities": {
        "hashtags": [],
        "symbols": [],
        "user_mentions": [],
        "urls": []
      },
      "source": "<a href=\"http://twitter.com\" rel=\"nofollow\">Twitter Web Client</a>",
      "in_reply_to_status_id": null,
      "in_reply_to_status_id_str": null,
      "in_reply_to_user_id": null,
      "in_reply_to_user_id_str": null,
      "in_reply_to_screen_name": null,
      "user": {
        "id": 747371158832545800,
        "id_str": "747371158832545792"
      },
      "geo": null,
      "coordinates": null,
      "place": null,
      "contributors": null,
      "is_quote_status": false,
      "retweet_count": 0,
      "favorite_count": 2,
      "favorited": false,
      "retweeted": false,
      "lang": "ru"
    },
    {
      "created_at": "Mon Nov 14 14:49:51 +0000 2016",
      "id": 798176122844442600,
      "id_str": "798176122844442624",
      "text": "Причем, желательно кооперативный платформер, и чтобы ВСЕ ВЗРЫВАЛОСЬ НА БОЛЬШОМ ЭКРАНЕ :D",
      "truncated": false,
      "entities": {
        "hashtags": [],
        "symbols": [],
        "user_mentions": [],
        "urls": []
      },
      "source": "<a href=\"http://twitter.com\" rel=\"nofollow\">Twitter Web Client</a>",
      "in_reply_to_status_id": 798168625253417000,
      "in_reply_to_status_id_str": "798168625253416960",
      "in_reply_to_user_id": 747371158832545800,
      "in_reply_to_user_id_str": "747371158832545792",
      "in_reply_to_screen_name": "gdunderhood",
      "user": {
        "id": 747371158832545800,
        "id_str": "747371158832545792"
      },
      "geo": null,
      "coordinates": null,
      "place": null,
      "contributors": null,
      "is_quote_status": false,
      "retweet_count": 0,
      "favorite_count": 1,
      "favorited": false,
      "retweeted": false,
      "lang": "ru"
    },
    {
      "created_at": "Mon Nov 14 15:26:53 +0000 2016",
      "id": 798185443422408700,
      "id_str": "798185443422408706",
      "text": "Забавное наблюдение: люди не воспринимают критику и советы на шоукейсах. Они приезжают похвастаться своей игрой, найти инвесторов, ресурсы.",
      "truncated": false,
      "entities": {
        "hashtags": [],
        "symbols": [],
        "user_mentions": [],
        "urls": []
      },
      "source": "<a href=\"http://twitter.com\" rel=\"nofollow\">Twitter Web Client</a>",
      "in_reply_to_status_id": null,
      "in_reply_to_status_id_str": null,
      "in_reply_to_user_id": null,
      "in_reply_to_user_id_str": null,
      "in_reply_to_screen_name": null,
      "user": {
        "id": 747371158832545800,
        "id_str": "747371158832545792"
      },
      "geo": null,
      "coordinates": null,
      "place": null,
      "contributors": null,
      "is_quote_status": false,
      "retweet_count": 1,
      "favorite_count": 4,
      "favorited": false,
      "retweeted": false,
      "lang": "ru"
    },
    {
      "created_at": "Mon Nov 14 15:37:40 +0000 2016",
      "id": 798188154670850000,
      "id_str": "798188154670850048",
      "text": "Самый популярный ответ разработчиков на критику с Линча и Анти-Линча: \"Мы только что выпустили новый билд, в котором всё это исправили\".",
      "truncated": false,
      "entities": {
        "hashtags": [],
        "symbols": [],
        "user_mentions": [],
        "urls": []
      },
      "source": "<a href=\"http://twitter.com\" rel=\"nofollow\">Twitter Web Client</a>",
      "in_reply_to_status_id": null,
      "in_reply_to_status_id_str": null,
      "in_reply_to_user_id": null,
      "in_reply_to_user_id_str": null,
      "in_reply_to_screen_name": null,
      "user": {
        "id": 747371158832545800,
        "id_str": "747371158832545792"
      },
      "geo": null,
      "coordinates": null,
      "place": null,
      "contributors": null,
      "is_quote_status": false,
      "retweet_count": 1,
      "favorite_count": 6,
      "favorited": false,
      "retweeted": false,
      "lang": "ru"
    },
    {
      "created_at": "Mon Nov 14 18:37:49 +0000 2016",
      "id": 798233491091652600,
      "id_str": "798233491091652609",
      "text": "Награждение Персон года 2016 прошло без сюрпризов, но Осташко Илья не терял надежды. https://t.co/MTHDhEmHpi",
      "truncated": false,
      "entities": {
        "hashtags": [],
        "symbols": [],
        "user_mentions": [],
        "urls": [],
        "media": [
          {
            "id": 798231245092175900,
            "id_str": "798231245092175872",
            "indices": [
              85,
              108
            ],
            "media_url": "http://pbs.twimg.com/tweet_video_thumb/CxPjFpRWQAAXNR0.jpg",
            "media_url_https": "https://pbs.twimg.com/tweet_video_thumb/CxPjFpRWQAAXNR0.jpg",
            "url": "https://t.co/MTHDhEmHpi",
            "display_url": "pic.twitter.com/MTHDhEmHpi",
            "expanded_url": "https://twitter.com/gdunderhood/status/798233491091652609/photo/1",
            "type": "photo",
            "sizes": {
              "large": {
                "w": 730,
                "h": 972,
                "resize": "fit"
              },
              "small": {
                "w": 340,
                "h": 453,
                "resize": "fit"
              },
              "thumb": {
                "w": 150,
                "h": 150,
                "resize": "crop"
              },
              "medium": {
                "w": 600,
                "h": 799,
                "resize": "fit"
              }
            }
          }
        ]
      },
      "extended_entities": {
        "media": [
          {
            "id": 798231245092175900,
            "id_str": "798231245092175872",
            "indices": [
              85,
              108
            ],
            "media_url": "http://pbs.twimg.com/tweet_video_thumb/CxPjFpRWQAAXNR0.jpg",
            "media_url_https": "https://pbs.twimg.com/tweet_video_thumb/CxPjFpRWQAAXNR0.jpg",
            "url": "https://t.co/MTHDhEmHpi",
            "display_url": "pic.twitter.com/MTHDhEmHpi",
            "expanded_url": "https://twitter.com/gdunderhood/status/798233491091652609/photo/1",
            "type": "animated_gif",
            "sizes": {
              "large": {
                "w": 730,
                "h": 972,
                "resize": "fit"
              },
              "small": {
                "w": 340,
                "h": 453,
                "resize": "fit"
              },
              "thumb": {
                "w": 150,
                "h": 150,
                "resize": "crop"
              },
              "medium": {
                "w": 600,
                "h": 799,
                "resize": "fit"
              }
            },
            "video_info": {
              "aspect_ratio": [
                365,
                486
              ],
              "variants": [
                {
                  "bitrate": 0,
                  "content_type": "video/mp4",
                  "url": "https://pbs.twimg.com/tweet_video/CxPjFpRWQAAXNR0.mp4"
                }
              ]
            }
          }
        ]
      },
      "source": "<a href=\"http://twitter.com\" rel=\"nofollow\">Twitter Web Client</a>",
      "in_reply_to_status_id": null,
      "in_reply_to_status_id_str": null,
      "in_reply_to_user_id": null,
      "in_reply_to_user_id_str": null,
      "in_reply_to_screen_name": null,
      "user": {
        "id": 747371158832545800,
        "id_str": "747371158832545792"
      },
      "geo": null,
      "coordinates": null,
      "place": null,
      "contributors": null,
      "is_quote_status": false,
      "retweet_count": 2,
      "favorite_count": 1,
      "favorited": false,
      "retweeted": false,
      "possibly_sensitive": false,
      "lang": "ru"
    },
    {
      "created_at": "Mon Nov 14 19:37:01 +0000 2016",
      "id": 798248388571648000,
      "id_str": "798248388571648000",
      "text": "Обычно обсуждать политику за столом считается моветоном.\nНа застолье #DevGAMM попросили завязывать про нарратив и переключились на Трампа.",
      "truncated": false,
      "entities": {
        "hashtags": [
          {
            "text": "DevGAMM",
            "indices": [
              69,
              77
            ]
          }
        ],
        "symbols": [],
        "user_mentions": [],
        "urls": []
      },
      "source": "<a href=\"http://twitter.com/download/android\" rel=\"nofollow\">Twitter for Android</a>",
      "in_reply_to_status_id": null,
      "in_reply_to_status_id_str": null,
      "in_reply_to_user_id": null,
      "in_reply_to_user_id_str": null,
      "in_reply_to_screen_name": null,
      "user": {
        "id": 747371158832545800,
        "id_str": "747371158832545792"
      },
      "geo": null,
      "coordinates": null,
      "place": null,
      "contributors": null,
      "is_quote_status": false,
      "retweet_count": 1,
      "favorite_count": 3,
      "favorited": false,
      "retweeted": false,
      "lang": "ru"
    },
    {
      "created_at": "Tue Nov 15 08:53:41 +0000 2016",
      "id": 798448876948783100,
      "id_str": "798448876948783108",
      "text": "Опрос участников #DevGAMM - во сколько вам обошлось жилье?\nНам двухэтажный коттедж на 7 человек вышел в 1700р за ночь за человека.",
      "truncated": false,
      "entities": {
        "hashtags": [
          {
            "text": "DevGAMM",
            "indices": [
              17,
              25
            ]
          }
        ],
        "symbols": [],
        "user_mentions": [],
        "urls": []
      },
      "source": "<a href=\"http://twitter.com/download/android\" rel=\"nofollow\">Twitter for Android</a>",
      "in_reply_to_status_id": null,
      "in_reply_to_status_id_str": null,
      "in_reply_to_user_id": null,
      "in_reply_to_user_id_str": null,
      "in_reply_to_screen_name": null,
      "user": {
        "id": 747371158832545800,
        "id_str": "747371158832545792"
      },
      "geo": null,
      "coordinates": null,
      "place": null,
      "contributors": null,
      "is_quote_status": false,
      "retweet_count": 0,
      "favorite_count": 0,
      "favorited": false,
      "retweeted": false,
      "lang": "ru"
    },
    {
      "created_at": "Tue Nov 15 10:38:09 +0000 2016",
      "id": 798475167135567900,
      "id_str": "798475167135567872",
      "text": "Несмотря на ужасный интернет, как Wi-Fi так и мобильный, удалось постримить завершающий кусочек нашего Анти-Линча.\nhttps://t.co/FIueTCJNBK",
      "truncated": false,
      "entities": {
        "hashtags": [],
        "symbols": [],
        "user_mentions": [],
        "urls": [
          {
            "url": "https://t.co/FIueTCJNBK",
            "expanded_url": "https://www.facebook.com/alfonsocorp/videos/1151700014865287",
            "display_url": "facebook.com/alfonsocorp/vi…",
            "indices": [
              115,
              138
            ]
          }
        ]
      },
      "source": "<a href=\"http://twitter.com\" rel=\"nofollow\">Twitter Web Client</a>",
      "in_reply_to_status_id": null,
      "in_reply_to_status_id_str": null,
      "in_reply_to_user_id": null,
      "in_reply_to_user_id_str": null,
      "in_reply_to_screen_name": null,
      "user": {
        "id": 747371158832545800,
        "id_str": "747371158832545792"
      },
      "geo": null,
      "coordinates": null,
      "place": null,
      "contributors": null,
      "is_quote_status": false,
      "retweet_count": 0,
      "favorite_count": 0,
      "favorited": false,
      "retweeted": false,
      "possibly_sensitive": false,
      "lang": "ru"
    },
    {
      "created_at": "Tue Nov 15 13:12:16 +0000 2016",
      "id": 798513951726338000,
      "id_str": "798513951726338048",
      "text": "@dearenot зачем инди делать сложный многоплановый проект?",
      "truncated": false,
      "entities": {
        "hashtags": [],
        "symbols": [],
        "user_mentions": [
          {
            "screen_name": "dearenot",
            "name": "Олег Попов",
            "id": 19496422,
            "id_str": "19496422",
            "indices": [
              0,
              9
            ]
          }
        ],
        "urls": []
      },
      "source": "<a href=\"http://twitter.com/download/android\" rel=\"nofollow\">Twitter for Android</a>",
      "in_reply_to_status_id": 798464158924763100,
      "in_reply_to_status_id_str": "798464158924763136",
      "in_reply_to_user_id": 19496422,
      "in_reply_to_user_id_str": "19496422",
      "in_reply_to_screen_name": "dearenot",
      "user": {
        "id": 747371158832545800,
        "id_str": "747371158832545792"
      },
      "geo": null,
      "coordinates": null,
      "place": null,
      "contributors": null,
      "is_quote_status": false,
      "retweet_count": 0,
      "favorite_count": 0,
      "favorited": false,
      "retweeted": false,
      "lang": "ru"
    },
    {
      "created_at": "Tue Nov 15 13:56:22 +0000 2016",
      "id": 798525049091129300,
      "id_str": "798525049091129344",
      "text": "Затронули обсуждение поездок на конференции.\nА как у вас в компании к этому относятся?",
      "truncated": false,
      "entities": {
        "hashtags": [],
        "symbols": [],
        "user_mentions": [],
        "urls": []
      },
      "source": "<a href=\"http://twitter.com\" rel=\"nofollow\">Twitter Web Client</a>",
      "in_reply_to_status_id": null,
      "in_reply_to_status_id_str": null,
      "in_reply_to_user_id": null,
      "in_reply_to_user_id_str": null,
      "in_reply_to_screen_name": null,
      "user": {
        "id": 747371158832545800,
        "id_str": "747371158832545792"
      },
      "geo": null,
      "coordinates": null,
      "place": null,
      "contributors": null,
      "is_quote_status": false,
      "retweet_count": 0,
      "favorite_count": 0,
      "favorited": false,
      "retweeted": false,
      "lang": "ru"
    },
    {
      "created_at": "Tue Nov 15 15:06:55 +0000 2016",
      "id": 798542804528009200,
      "id_str": "798542804528009217",
      "text": "@dearenot чувствуется рука мастера.",
      "truncated": false,
      "entities": {
        "hashtags": [],
        "symbols": [],
        "user_mentions": [
          {
            "screen_name": "dearenot",
            "name": "Олег Попов",
            "id": 19496422,
            "id_str": "19496422",
            "indices": [
              0,
              9
            ]
          }
        ],
        "urls": []
      },
      "source": "<a href=\"http://twitter.com/download/android\" rel=\"nofollow\">Twitter for Android</a>",
      "in_reply_to_status_id": 798541514842345500,
      "in_reply_to_status_id_str": "798541514842345473",
      "in_reply_to_user_id": 19496422,
      "in_reply_to_user_id_str": "19496422",
      "in_reply_to_screen_name": "dearenot",
      "user": {
        "id": 747371158832545800,
        "id_str": "747371158832545792"
      },
      "geo": null,
      "coordinates": null,
      "place": null,
      "contributors": null,
      "is_quote_status": false,
      "retweet_count": 0,
      "favorite_count": 0,
      "favorited": false,
      "retweeted": false,
      "lang": "ru"
    },
    {
      "created_at": "Tue Nov 15 17:17:15 +0000 2016",
      "id": 798575605289783300,
      "id_str": "798575605289783296",
      "text": "На волне предыдущего опроса сразу следующий.\nКакая ваша основная цель на конференциях?",
      "truncated": false,
      "entities": {
        "hashtags": [],
        "symbols": [],
        "user_mentions": [],
        "urls": []
      },
      "source": "<a href=\"http://twitter.com/download/android\" rel=\"nofollow\">Twitter for Android</a>",
      "in_reply_to_status_id": null,
      "in_reply_to_status_id_str": null,
      "in_reply_to_user_id": null,
      "in_reply_to_user_id_str": null,
      "in_reply_to_screen_name": null,
      "user": {
        "id": 747371158832545800,
        "id_str": "747371158832545792"
      },
      "geo": null,
      "coordinates": null,
      "place": null,
      "contributors": null,
      "is_quote_status": false,
      "retweet_count": 1,
      "favorite_count": 1,
      "favorited": false,
      "retweeted": false,
      "lang": "ru"
    },
    {
      "created_at": "Wed Nov 16 09:10:51 +0000 2016",
      "id": 798815585089953800,
      "id_str": "798815585089953792",
      "text": "Изначально наша поездка на #DevGAMM планировалась коллективной от лица Манжет ГД. Но только один указал на бейдже не реальное место работы.",
      "truncated": false,
      "entities": {
        "hashtags": [
          {
            "text": "DevGAMM",
            "indices": [
              27,
              35
            ]
          }
        ],
        "symbols": [],
        "user_mentions": [],
        "urls": []
      },
      "source": "<a href=\"http://twitter.com/download/android\" rel=\"nofollow\">Twitter for Android</a>",
      "in_reply_to_status_id": null,
      "in_reply_to_status_id_str": null,
      "in_reply_to_user_id": null,
      "in_reply_to_user_id_str": null,
      "in_reply_to_screen_name": null,
      "user": {
        "id": 747371158832545800,
        "id_str": "747371158832545792"
      },
      "geo": null,
      "coordinates": null,
      "place": null,
      "contributors": null,
      "is_quote_status": false,
      "retweet_count": 0,
      "favorite_count": 0,
      "favorited": false,
      "retweeted": false,
      "lang": "ru"
    },
    {
      "created_at": "Wed Nov 16 11:23:47 +0000 2016",
      "id": 798849037780668400,
      "id_str": "798849037780668417",
      "text": "Любопытный факт: чем позднее афтерпати, тем ценнее инсайды.",
      "truncated": false,
      "entities": {
        "hashtags": [],
        "symbols": [],
        "user_mentions": [],
        "urls": []
      },
      "source": "<a href=\"http://twitter.com\" rel=\"nofollow\">Twitter Web Client</a>",
      "in_reply_to_status_id": null,
      "in_reply_to_status_id_str": null,
      "in_reply_to_user_id": null,
      "in_reply_to_user_id_str": null,
      "in_reply_to_screen_name": null,
      "user": {
        "id": 747371158832545800,
        "id_str": "747371158832545792"
      },
      "geo": null,
      "coordinates": null,
      "place": null,
      "contributors": null,
      "is_quote_status": false,
      "retweet_count": 0,
      "favorite_count": 3,
      "favorited": false,
      "retweeted": false,
      "lang": "ru"
    },
    {
      "created_at": "Wed Nov 16 12:56:26 +0000 2016",
      "id": 798872357360271400,
      "id_str": "798872357360271360",
      "text": "Специально брали дом с камином, баней и шашлычками.\nВ баню приходилось людей розгами загонять, камин и шашлыки так ниразу и не разожгли.",
      "truncated": false,
      "entities": {
        "hashtags": [],
        "symbols": [],
        "user_mentions": [],
        "urls": []
      },
      "source": "<a href=\"http://twitter.com\" rel=\"nofollow\">Twitter Web Client</a>",
      "in_reply_to_status_id": null,
      "in_reply_to_status_id_str": null,
      "in_reply_to_user_id": null,
      "in_reply_to_user_id_str": null,
      "in_reply_to_screen_name": null,
      "user": {
        "id": 747371158832545800,
        "id_str": "747371158832545792"
      },
      "geo": null,
      "coordinates": null,
      "place": null,
      "contributors": null,
      "is_quote_status": false,
      "retweet_count": 0,
      "favorite_count": 0,
      "favorited": false,
      "retweeted": false,
      "lang": "ru"
    },
    {
      "created_at": "Wed Nov 16 14:55:40 +0000 2016",
      "id": 798902359753691100,
      "id_str": "798902359753691136",
      "text": "Вторые сутки конференции, час ночи, @GDcuffs после афтерпати собираются спать.\nПриезжают братья Арамяны, уезжают в пять. Отличные ребята.",
      "truncated": false,
      "entities": {
        "hashtags": [],
        "symbols": [],
        "user_mentions": [
          {
            "screen_name": "GDcuffs",
            "name": "Манжеты ГД",
            "id": 3341695624,
            "id_str": "3341695624",
            "indices": [
              36,
              44
            ]
          }
        ],
        "urls": []
      },
      "source": "<a href=\"http://twitter.com\" rel=\"nofollow\">Twitter Web Client</a>",
      "in_reply_to_status_id": null,
      "in_reply_to_status_id_str": null,
      "in_reply_to_user_id": null,
      "in_reply_to_user_id_str": null,
      "in_reply_to_screen_name": null,
      "user": {
        "id": 747371158832545800,
        "id_str": "747371158832545792"
      },
      "geo": null,
      "coordinates": null,
      "place": null,
      "contributors": null,
      "is_quote_status": false,
      "retweet_count": 0,
      "favorite_count": 0,
      "favorited": false,
      "retweeted": false,
      "lang": "ru"
    },
    {
      "created_at": "Wed Nov 16 17:57:38 +0000 2016",
      "id": 798948154339115000,
      "id_str": "798948154339115008",
      "text": "Лайфхак для потеряшек: красить волосы в яркий цвет это не только красиво, но и полезно.\nНу или купите яркую кепку (только не оранжевую).",
      "truncated": false,
      "entities": {
        "hashtags": [],
        "symbols": [],
        "user_mentions": [],
        "urls": []
      },
      "source": "<a href=\"http://twitter.com\" rel=\"nofollow\">Twitter Web Client</a>",
      "in_reply_to_status_id": null,
      "in_reply_to_status_id_str": null,
      "in_reply_to_user_id": null,
      "in_reply_to_user_id_str": null,
      "in_reply_to_screen_name": null,
      "user": {
        "id": 747371158832545800,
        "id_str": "747371158832545792"
      },
      "geo": null,
      "coordinates": null,
      "place": null,
      "contributors": null,
      "is_quote_status": false,
      "retweet_count": 0,
      "favorite_count": 1,
      "favorited": false,
      "retweeted": false,
      "lang": "ru"
    },
    {
      "created_at": "Thu Nov 17 08:55:47 +0000 2016",
      "id": 799174181346742300,
      "id_str": "799174181346742272",
      "text": "MARIA CHYRVONA: \"Интернет на конференции - это единорог\".\nНикогда. На него. Не рассчитывайте.",
      "truncated": false,
      "entities": {
        "hashtags": [],
        "symbols": [],
        "user_mentions": [],
        "urls": []
      },
      "source": "<a href=\"http://twitter.com/download/android\" rel=\"nofollow\">Twitter for Android</a>",
      "in_reply_to_status_id": null,
      "in_reply_to_status_id_str": null,
      "in_reply_to_user_id": null,
      "in_reply_to_user_id_str": null,
      "in_reply_to_screen_name": null,
      "user": {
        "id": 747371158832545800,
        "id_str": "747371158832545792"
      },
      "geo": null,
      "coordinates": null,
      "place": null,
      "contributors": null,
      "is_quote_status": false,
      "retweet_count": 0,
      "favorite_count": 1,
      "favorited": false,
      "retweeted": false,
      "lang": "ru"
    },
    {
      "created_at": "Thu Nov 17 10:21:45 +0000 2016",
      "id": 799195816518942700,
      "id_str": "799195816518942720",
      "text": "#DevGAMM - это как поход в магазин.\nЕсли заранее не составить точный план действий - накупишь кучу всего, а пожрать все равно будет нечего.",
      "truncated": false,
      "entities": {
        "hashtags": [
          {
            "text": "DevGAMM",
            "indices": [
              0,
              8
            ]
          }
        ],
        "symbols": [],
        "user_mentions": [],
        "urls": []
      },
      "source": "<a href=\"http://twitter.com\" rel=\"nofollow\">Twitter Web Client</a>",
      "in_reply_to_status_id": null,
      "in_reply_to_status_id_str": null,
      "in_reply_to_user_id": null,
      "in_reply_to_user_id_str": null,
      "in_reply_to_screen_name": null,
      "user": {
        "id": 747371158832545800,
        "id_str": "747371158832545792"
      },
      "geo": null,
      "coordinates": null,
      "place": null,
      "contributors": null,
      "is_quote_status": false,
      "retweet_count": 1,
      "favorite_count": 2,
      "favorited": false,
      "retweeted": false,
      "lang": "ru"
    },
    {
      "created_at": "Thu Nov 17 14:41:08 +0000 2016",
      "id": 799261090534170600,
      "id_str": "799261090534170625",
      "text": "Если вы хотите с кем-то встретиться на конференции - постарайтесь это сделать в первый день.\nВозможно завтра его уже не будет. Или вас.",
      "truncated": false,
      "entities": {
        "hashtags": [],
        "symbols": [],
        "user_mentions": [],
        "urls": []
      },
      "source": "<a href=\"http://twitter.com\" rel=\"nofollow\">Twitter Web Client</a>",
      "in_reply_to_status_id": null,
      "in_reply_to_status_id_str": null,
      "in_reply_to_user_id": null,
      "in_reply_to_user_id_str": null,
      "in_reply_to_screen_name": null,
      "user": {
        "id": 747371158832545800,
        "id_str": "747371158832545792"
      },
      "geo": null,
      "coordinates": null,
      "place": null,
      "contributors": null,
      "is_quote_status": false,
      "retweet_count": 0,
      "favorite_count": 1,
      "favorited": false,
      "retweeted": false,
      "lang": "ru"
    },
    {
      "created_at": "Thu Nov 17 16:19:51 +0000 2016",
      "id": 799285936009990100,
      "id_str": "799285936009990144",
      "text": "Так как возможности твиттера несколько ограничены символами - выпустили целую статью о участии @GDcuffs в #DevGAMM… https://t.co/7ZIAKEF35m",
      "truncated": true,
      "entities": {
        "hashtags": [
          {
            "text": "DevGAMM",
            "indices": [
              106,
              114
            ]
          }
        ],
        "symbols": [],
        "user_mentions": [
          {
            "screen_name": "GDcuffs",
            "name": "Манжеты ГД",
            "id": 3341695624,
            "id_str": "3341695624",
            "indices": [
              95,
              103
            ]
          }
        ],
        "urls": [
          {
            "url": "https://t.co/7ZIAKEF35m",
            "expanded_url": "https://twitter.com/i/web/status/799285936009990144",
            "display_url": "twitter.com/i/web/status/7…",
            "indices": [
              116,
              139
            ]
          }
        ]
      },
      "source": "<a href=\"http://twitter.com\" rel=\"nofollow\">Twitter Web Client</a>",
      "in_reply_to_status_id": null,
      "in_reply_to_status_id_str": null,
      "in_reply_to_user_id": null,
      "in_reply_to_user_id_str": null,
      "in_reply_to_screen_name": null,
      "user": {
        "id": 747371158832545800,
        "id_str": "747371158832545792"
      },
      "geo": null,
      "coordinates": null,
      "place": null,
      "contributors": null,
      "is_quote_status": false,
      "retweet_count": 1,
      "favorite_count": 3,
      "favorited": false,
      "retweeted": false,
      "possibly_sensitive": false,
      "lang": "ru"
    },
    {
      "created_at": "Thu Nov 17 18:25:53 +0000 2016",
      "id": 799317653324267500,
      "id_str": "799317653324267520",
      "text": "Главной проблемой #DevGAMM лично для меня стал выбор докладов. Я как игрок - не люблю выбирать.\nВ итоге не посетил ни один.",
      "truncated": false,
      "entities": {
        "hashtags": [
          {
            "text": "DevGAMM",
            "indices": [
              18,
              26
            ]
          }
        ],
        "symbols": [],
        "user_mentions": [],
        "urls": []
      },
      "source": "<a href=\"http://twitter.com/download/android\" rel=\"nofollow\">Twitter for Android</a>",
      "in_reply_to_status_id": null,
      "in_reply_to_status_id_str": null,
      "in_reply_to_user_id": null,
      "in_reply_to_user_id_str": null,
      "in_reply_to_screen_name": null,
      "user": {
        "id": 747371158832545800,
        "id_str": "747371158832545792"
      },
      "geo": null,
      "coordinates": null,
      "place": null,
      "contributors": null,
      "is_quote_status": false,
      "retweet_count": 0,
      "favorite_count": 2,
      "favorited": false,
      "retweeted": false,
      "lang": "ru"
    },
    {
      "created_at": "Fri Nov 18 09:20:38 +0000 2016",
      "id": 799542824098263000,
      "id_str": "799542824098263040",
      "text": "Очень не хватало на бейджах #DevGAMM уровня персонажа.\nИ если с Легендарными NPC все более-менее понятно, то градации ниже мешались в кучу.",
      "truncated": false,
      "entities": {
        "hashtags": [
          {
            "text": "DevGAMM",
            "indices": [
              28,
              36
            ]
          }
        ],
        "symbols": [],
        "user_mentions": [],
        "urls": []
      },
      "source": "<a href=\"http://twitter.com/download/android\" rel=\"nofollow\">Twitter for Android</a>",
      "in_reply_to_status_id": null,
      "in_reply_to_status_id_str": null,
      "in_reply_to_user_id": null,
      "in_reply_to_user_id_str": null,
      "in_reply_to_screen_name": null,
      "user": {
        "id": 747371158832545800,
        "id_str": "747371158832545792"
      },
      "geo": null,
      "coordinates": null,
      "place": null,
      "contributors": null,
      "is_quote_status": false,
      "retweet_count": 0,
      "favorite_count": 0,
      "favorited": false,
      "retweeted": false,
      "lang": "ru"
    },
    {
      "created_at": "Fri Nov 18 11:09:54 +0000 2016",
      "id": 799570320025714700,
      "id_str": "799570320025714688",
      "text": "Порадовала инициатива оргов на ужине для спикеров - попросили садиться с незнакомыми людьми (нетворкинг).\nНо надо было жестче, рассаживать.",
      "truncated": false,
      "entities": {
        "hashtags": [],
        "symbols": [],
        "user_mentions": [],
        "urls": []
      },
      "source": "<a href=\"http://twitter.com\" rel=\"nofollow\">Twitter Web Client</a>",
      "in_reply_to_status_id": null,
      "in_reply_to_status_id_str": null,
      "in_reply_to_user_id": null,
      "in_reply_to_user_id_str": null,
      "in_reply_to_screen_name": null,
      "user": {
        "id": 747371158832545800,
        "id_str": "747371158832545792"
      },
      "geo": null,
      "coordinates": null,
      "place": null,
      "contributors": null,
      "is_quote_status": false,
      "retweet_count": 0,
      "favorite_count": 1,
      "favorited": false,
      "retweeted": false,
      "lang": "ru"
    },
    {
      "created_at": "Fri Nov 18 14:02:26 +0000 2016",
      "id": 799613740689735700,
      "id_str": "799613740689735681",
      "text": "Подчерпнул для себя полезную мысль: берите с собой минимум вещей и не стройте лишних планов.\nКонференция сожрет всё ваше время.",
      "truncated": false,
      "entities": {
        "hashtags": [],
        "symbols": [],
        "user_mentions": [],
        "urls": []
      },
      "source": "<a href=\"http://twitter.com\" rel=\"nofollow\">Twitter Web Client</a>",
      "in_reply_to_status_id": null,
      "in_reply_to_status_id_str": null,
      "in_reply_to_user_id": null,
      "in_reply_to_user_id_str": null,
      "in_reply_to_screen_name": null,
      "user": {
        "id": 747371158832545800,
        "id_str": "747371158832545792"
      },
      "geo": null,
      "coordinates": null,
      "place": null,
      "contributors": null,
      "is_quote_status": false,
      "retweet_count": 0,
      "favorite_count": 0,
      "favorited": false,
      "retweeted": false,
      "lang": "ru"
    },
    {
      "created_at": "Fri Nov 18 15:24:28 +0000 2016",
      "id": 799634385884639200,
      "id_str": "799634385884639233",
      "text": "Самые милые создания на конференции - это девочки, продающие трафик.\nКак их вычислить? Они подходят знакомиться к геймдизайнерам.",
      "truncated": false,
      "entities": {
        "hashtags": [],
        "symbols": [],
        "user_mentions": [],
        "urls": []
      },
      "source": "<a href=\"http://twitter.com\" rel=\"nofollow\">Twitter Web Client</a>",
      "in_reply_to_status_id": null,
      "in_reply_to_status_id_str": null,
      "in_reply_to_user_id": null,
      "in_reply_to_user_id_str": null,
      "in_reply_to_screen_name": null,
      "user": {
        "id": 747371158832545800,
        "id_str": "747371158832545792"
      },
      "geo": null,
      "coordinates": null,
      "place": null,
      "contributors": null,
      "is_quote_status": false,
      "retweet_count": 0,
      "favorite_count": 2,
      "favorited": false,
      "retweeted": false,
      "lang": "ru"
    },
    {
      "created_at": "Fri Nov 18 19:24:43 +0000 2016",
      "id": 799694845661081600,
      "id_str": "799694845661081602",
      "text": "@wasteland_rider Не обычно. Никогда.\nУ ГД нет девушек не считая тех, которых они получили до того как стали ГД.",
      "truncated": false,
      "entities": {
        "hashtags": [],
        "symbols": [],
        "user_mentions": [
          {
            "screen_name": "wasteland_rider",
            "name": "Vitaly Grischenckoff",
            "id": 48675889,
            "id_str": "48675889",
            "indices": [
              0,
              16
            ]
          }
        ],
        "urls": []
      },
      "source": "<a href=\"http://twitter.com/download/android\" rel=\"nofollow\">Twitter for Android</a>",
      "in_reply_to_status_id": 799671883415298000,
      "in_reply_to_status_id_str": "799671883415298049",
      "in_reply_to_user_id": 48675889,
      "in_reply_to_user_id_str": "48675889",
      "in_reply_to_screen_name": "wasteland_rider",
      "user": {
        "id": 747371158832545800,
        "id_str": "747371158832545792"
      },
      "geo": null,
      "coordinates": null,
      "place": null,
      "contributors": null,
      "is_quote_status": false,
      "retweet_count": 0,
      "favorite_count": 0,
      "favorited": false,
      "retweeted": false,
      "lang": "ru"
    },
    {
      "created_at": "Fri Nov 18 20:07:28 +0000 2016",
      "id": 799705602872250400,
      "id_str": "799705602872250368",
      "text": "Вам никогда не казалось, что конференциям не хватает серьезной геймификации? Как в ролевках, с разными сеттингами каждый год.",
      "truncated": false,
      "entities": {
        "hashtags": [],
        "symbols": [],
        "user_mentions": [],
        "urls": []
      },
      "source": "<a href=\"http://twitter.com/download/android\" rel=\"nofollow\">Twitter for Android</a>",
      "in_reply_to_status_id": null,
      "in_reply_to_status_id_str": null,
      "in_reply_to_user_id": null,
      "in_reply_to_user_id_str": null,
      "in_reply_to_screen_name": null,
      "user": {
        "id": 747371158832545800,
        "id_str": "747371158832545792"
      },
      "geo": null,
      "coordinates": null,
      "place": null,
      "contributors": null,
      "is_quote_status": false,
      "retweet_count": 0,
      "favorite_count": 2,
      "favorited": false,
      "retweeted": false,
      "lang": "ru"
    },
    {
      "created_at": "Fri Nov 18 20:10:38 +0000 2016",
      "id": 799706399567708200,
      "id_str": "799706399567708164",
      "text": "Чтобы с NPC и мобами, квестами и наградами, рейдами и лутом, кланами и экспой.\nВсе то же самое, но не в лоб, а в красивой обертке.",
      "truncated": false,
      "entities": {
        "hashtags": [],
        "symbols": [],
        "user_mentions": [],
        "urls": []
      },
      "source": "<a href=\"http://twitter.com/download/android\" rel=\"nofollow\">Twitter for Android</a>",
      "in_reply_to_status_id": null,
      "in_reply_to_status_id_str": null,
      "in_reply_to_user_id": null,
      "in_reply_to_user_id_str": null,
      "in_reply_to_screen_name": null,
      "user": {
        "id": 747371158832545800,
        "id_str": "747371158832545792"
      },
      "geo": null,
      "coordinates": null,
      "place": null,
      "contributors": null,
      "is_quote_status": false,
      "retweet_count": 0,
      "favorite_count": 0,
      "favorited": false,
      "retweeted": false,
      "lang": "ru"
    },
    {
      "created_at": "Fri Nov 18 20:15:04 +0000 2016",
      "id": 799707518322688000,
      "id_str": "799707518322688001",
      "text": "На ресепшене стартуешь сюжетную линию, за доклады получаешь экспу, по ходу получаешь побочные квесты, входишь в группу для сложных задач.",
      "truncated": false,
      "entities": {
        "hashtags": [],
        "symbols": [],
        "user_mentions": [],
        "urls": []
      },
      "source": "<a href=\"http://twitter.com/download/android\" rel=\"nofollow\">Twitter for Android</a>",
      "in_reply_to_status_id": null,
      "in_reply_to_status_id_str": null,
      "in_reply_to_user_id": null,
      "in_reply_to_user_id_str": null,
      "in_reply_to_screen_name": null,
      "user": {
        "id": 747371158832545800,
        "id_str": "747371158832545792"
      },
      "geo": null,
      "coordinates": null,
      "place": null,
      "contributors": null,
      "is_quote_status": false,
      "retweet_count": 0,
      "favorite_count": 2,
      "favorited": false,
      "retweeted": false,
      "lang": "ru"
    },
    {
      "created_at": "Fri Nov 18 20:16:50 +0000 2016",
      "id": 799707963372040200,
      "id_str": "799707963372040193",
      "text": "Все манипуляции проходят через приложение на телефоне, в конце конференции подводятся итоги, в следующем году прогресс сохраняется.",
      "truncated": false,
      "entities": {
        "hashtags": [],
        "symbols": [],
        "user_mentions": [],
        "urls": []
      },
      "source": "<a href=\"http://twitter.com/download/android\" rel=\"nofollow\">Twitter for Android</a>",
      "in_reply_to_status_id": null,
      "in_reply_to_status_id_str": null,
      "in_reply_to_user_id": null,
      "in_reply_to_user_id_str": null,
      "in_reply_to_screen_name": null,
      "user": {
        "id": 747371158832545800,
        "id_str": "747371158832545792"
      },
      "geo": null,
      "coordinates": null,
      "place": null,
      "contributors": null,
      "is_quote_status": false,
      "retweet_count": 0,
      "favorite_count": 0,
      "favorited": false,
      "retweeted": false,
      "lang": "ru"
    },
    {
      "created_at": "Fri Nov 18 21:32:04 +0000 2016",
      "id": 799726894291636200,
      "id_str": "799726894291636225",
      "text": "@wasteland_rider Манжеты ГД - показать все что скрыто.",
      "truncated": false,
      "entities": {
        "hashtags": [],
        "symbols": [],
        "user_mentions": [
          {
            "screen_name": "wasteland_rider",
            "name": "Vitaly Grischenckoff",
            "id": 48675889,
            "id_str": "48675889",
            "indices": [
              0,
              16
            ]
          }
        ],
        "urls": []
      },
      "source": "<a href=\"http://twitter.com/download/android\" rel=\"nofollow\">Twitter for Android</a>",
      "in_reply_to_status_id": 799711754456440800,
      "in_reply_to_status_id_str": "799711754456440832",
      "in_reply_to_user_id": 48675889,
      "in_reply_to_user_id_str": "48675889",
      "in_reply_to_screen_name": "wasteland_rider",
      "user": {
        "id": 747371158832545800,
        "id_str": "747371158832545792"
      },
      "geo": null,
      "coordinates": null,
      "place": null,
      "contributors": null,
      "is_quote_status": false,
      "retweet_count": 0,
      "favorite_count": 0,
      "favorited": false,
      "retweeted": false,
      "lang": "ru"
    }
  ]
}
